LICENSE
README.md
setup.py
nearface/NearFace.py
nearface/__init__.py
nearface.egg-info/PKG-INFO
nearface.egg-info/SOURCES.txt
nearface.egg-info/dependency_links.txt
nearface.egg-info/requires.txt
nearface.egg-info/top_level.txt
nearface/basemodels/ArcFace.py
nearface/basemodels/Boosting.py
nearface/basemodels/DeepID.py
nearface/basemodels/DlibResNet.py
nearface/basemodels/DlibWrapper.py
nearface/basemodels/Facenet.py
nearface/basemodels/Facenet512.py
nearface/basemodels/FbDeepFace.py
nearface/basemodels/OpenFace.py
nearface/basemodels/VGGFace.py
nearface/basemodels/__init__.py
nearface/commons/__init__.py
nearface/commons/distance.py
nearface/commons/functions.py
nearface/commons/realtime.py
nearface/detectors/DlibWrapper.py
nearface/detectors/FaceDetector.py
nearface/detectors/MediapipeWrapper.py
nearface/detectors/MtcnnWrapper.py
nearface/detectors/OpenCvWrapper.py
nearface/detectors/RetinaFaceWrapper.py
nearface/detectors/SsdWrapper.py
nearface/detectors/__init__.py
nearface/extendedmodels/Age.py
nearface/extendedmodels/Emotion.py
nearface/extendedmodels/Gender.py
nearface/extendedmodels/Race.py
nearface/extendedmodels/__init__.py
nearface/models/__init__.py
nearface/models/face-recognition-ensemble-model.txt