Metadata-Version: 2.1
Name: nearface
Version: 0.1.4
Summary: A refined version of the Python library DeepFace
Home-page: https://github.com/palmtrey/nearface
Author: Cameron Palmer
Author-email: palmtrey779@gmail.com
License: UNKNOWN
Platform: UNKNOWN
Classifier: Programming Language :: Python :: 3
Classifier: License :: OSI Approved :: MIT License
Classifier: Operating System :: OS Independent
Requires-Python: >=3.5.5
License-File: LICENSE
